scrap_yahoo/__init__.py
scrap_yahoo/main.py
scrap_yahoo/scrap_mod.py
scrap_yahoo-0.0.2.dist-info/METADATA
scrap_yahoo-0.0.2.dist-info/WHEEL
scrap_yahoo-0.0.2.dist-info/top_level.txt
scrap_yahoo-0.0.2.dist-info/RECORD
