Metadata-Version: 2.1
Name: scrap-yahoo
Version: 0.0.2
Summary: A basic yahoo finance scraping package
Home-page: UNKNOWN
Author: JerryChenz (jerry Chen)
Author-email: <jerrychen.works@gmail.com>
License: UNKNOWN
Keywords: python,yahoo,financial statements
Platform: UNKNOWN
Classifier: Development Status :: 1 - Planning
Classifier: Intended Audience :: Developers
Classifier: Programming Language :: Python :: 3
Classifier: Operating System :: Unix
Classifier: Operating System :: MacOS :: MacOS X
Classifier: Operating System :: Microsoft :: Windows
Requires-Dist: bs4
Requires-Dist: requests
Requires-Dist: pandas
Requires-Dist: forex-python
